pygalfitm/__init__.py
pygalfitm/auxiliars.py
pygalfitm/log.py
pygalfitm/plot.py
pygalfitm/psf.py
pygalfitm/pygalfitm.py
pygalfitm/read.py
pygalfitm/VOs/__init__.py
pygalfitm/VOs/splus.py
pygalfitm/VOs/utils.py
pygalfitm-1.52.dist-info/METADATA
pygalfitm-1.52.dist-info/WHEEL
pygalfitm-1.52.dist-info/top_level.txt
pygalfitm-1.52.dist-info/RECORD
