Metadata-Version: 2.4
Name: pygalfitm
Version: 1.52
Summary: Python3 GalfitM wrapper
Home-page: https://github.com/schwarzam/pygalfitm
Author: Gustavo Schwarz
Author-email: gustavo.b.schwarz@gmail.com
Classifier: Programming Language :: Python :: 3
Classifier: License :: OSI Approved :: Apache Software License
Requires-Dist: astropy
Requires-Dist: pandas
Requires-Dist: numpy
Requires-Dist: requests
Requires-Dist: matplotlib
Requires-Dist: adss
Dynamic: author
Dynamic: author-email
Dynamic: classifier
Dynamic: home-page
Dynamic: requires-dist
Dynamic: summary
